cache/__init__.py
cameo_cache/__init__.py
cameo_cache/cameo_cache.py
cameo_cache-0.4.1.dist-info/METADATA
cameo_cache-0.4.1.dist-info/WHEEL
cameo_cache-0.4.1.dist-info/top_level.txt
cameo_cache-0.4.1.dist-info/RECORD
