Metadata-Version: 2.1
Name: cameo-cache
Version: 0.4.1
Summary: Google cloud storage cache for any slow web API.
Home-page: https://github.com/bohachu/cameo_cache
Author: Bowen Chiu
Author-email: bohachu@gmail.com
License: UNKNOWN
Platform: UNKNOWN
Classifier: Programming Language :: Python :: 3
Classifier: License :: OSI Approved :: MIT License
Classifier: Operating System :: OS Independent
